iacopilot/__init__.py
iacopilot/__main__.py
iacopilot-0.1.3b1.dist-info/LICENSE
iacopilot-0.1.3b1.dist-info/METADATA
iacopilot-0.1.3b1.dist-info/WHEEL
iacopilot-0.1.3b1.dist-info/entry_points.txt
iacopilot-0.1.3b1.dist-info/top_level.txt
iacopilot-0.1.3b1.dist-info/zip-safe
iacopilot-0.1.3b1.dist-info/RECORD
