Metadata-Version: 2.1
Name: iacopilot
Version: 0.1.3b1
Summary: Summarize and ask questions about items in the Internet Archive
Home-page: https://github.com/internetarchive/iacopilot
Author: Sawood Alam
Author-email: sawood@archive.org
Classifier: Programming Language :: Python :: 3
Classifier: License :: OSI Approved :: GNU Affero General Public License v3
Classifier: Operating System :: OS Independent
Classifier: Topic :: Scientific/Engineering :: Artificial Intelligence
Classifier: Topic :: System :: Archiving
Classifier: Topic :: Text Processing :: Indexing
Classifier: Topic :: Internet :: WWW/HTTP
Classifier: Topic :: Internet :: WWW/HTTP :: Indexing/Search
Provides: iacopilot
Requires-Python: >=3.6
License-File: LICENSE
Requires-Dist: internetarchive
Requires-Dist: llama-index
Requires-Dist: openai
Requires-Dist: pydantic
Requires-Dist: requests
Requires-Dist: rich
